setup.py
telegraph/__init__.py
telegraph/api.py
telegraph/types.py
telegraph/utils.py
telegraph_client.egg-info/PKG-INFO
telegraph_client.egg-info/SOURCES.txt
telegraph_client.egg-info/dependency_links.txt
telegraph_client.egg-info/requires.txt
telegraph_client.egg-info/top_level.txt