Metadata-Version: 1.2
Name: telegraph-client
Version: 0.1.0
Summary: Client and utilities for the Telegraph blogging service provided by Telegram.
Home-page: https://github.com/jacoduplessis/telegraph
Author: Jaco du Plessis
Author-email: jaco@jacoduplessis.co.za
License: UNKNOWN
Keywords: telegraph client telegram
Platform: UNKNOWN
Classifier: Development Status :: 3 - Alpha
Classifier: Intended Audience :: Developers
Classifier: License :: OSI Approved :: MIT License
Classifier: Programming Language :: Python :: 3
Classifier: Programming Language :: Python :: 3.6
Requires-Python: >=3.6
